MANIFEST.in
README.txt
setup.py
collective/__init__.py
collective.powertoken.workflow.egg-info/PKG-INFO
collective.powertoken.workflow.egg-info/SOURCES.txt
collective.powertoken.workflow.egg-info/dependency_links.txt
collective.powertoken.workflow.egg-info/entry_points.txt
collective.powertoken.workflow.egg-info/namespace_packages.txt
collective.powertoken.workflow.egg-info/not-zip-safe
collective.powertoken.workflow.egg-info/requires.txt
collective.powertoken.workflow.egg-info/top_level.txt
collective/powertoken/__init__.py
collective/powertoken/workflow/__init__.py
collective/powertoken/workflow/action.py
collective/powertoken/workflow/configure.zcml
collective/powertoken/workflow/tests/__init__.py
collective/powertoken/workflow/tests/base.py
collective/powertoken/workflow/tests/test_action.py
docs/HISTORY.txt
docs/INSTALL.txt
docs/LICENSE.GPL
docs/LICENSE.txt